qm9load/__init__.py
qm9load/load_qm9.py
qm9loader-0.4.dist-info/METADATA
qm9loader-0.4.dist-info/WHEEL
qm9loader-0.4.dist-info/top_level.txt
qm9loader-0.4.dist-info/RECORD
