Metadata-Version: 2.1
Name: qm9loader
Version: 0.4
Summary: Uploads current (4/16/24) version of QM9 to dataframe object
Author: Logan Snider
Author-email: logop1112@gmail.com
